CS_HELLO/__init__.py
CS_HELLO/main.py
CS_HELLO-0.2.0.dist-info/METADATA
CS_HELLO-0.2.0.dist-info/WHEEL
CS_HELLO-0.2.0.dist-info/top_level.txt
CS_HELLO-0.2.0.dist-info/RECORD
