Metadata-Version: 2.1
Name: CS_HELLO
Version: 0.2.0
